setup.py
./__init__.py
./api.py
jaconda.egg-info/PKG-INFO
jaconda.egg-info/SOURCES.txt
jaconda.egg-info/dependency_links.txt
jaconda.egg-info/requires.txt
jaconda.egg-info/top_level.txt