Metadata-Version: 1.0
Name: jaconda
Version: 0.1
Summary: Python client to Jaconda API v2
Home-page: http://openlabs.co.in
Author: Sharoon Thomas, Openlabs Technologies & Consulting (P) Limited
Author-email: sales@openlabs.co.in
License: BSD
Platform: UNKNOWN
Classifier: Development Status :: 1 - Planning
Classifier: License :: OSI Approved :: BSD License
Classifier: Natural Language :: English
Classifier: Topic :: Communications :: Chat
